vmc/__init__.py
vmc/callback/__init__.py
vmc/callback/base.py
vmc/callback/callbacks.py
vmc/callback/lark.py
vmc/cli.py
vmc/context/request.py
vmc/context/user.py
vmc/db/__init__.py
vmc/db/backend/disk_storage.py
vmc/db/backend/mongodb.py
vmc/db/db.py
vmc/db/schema.py
vmc/db/storage.py
vmc/exception.py
vmc/models/__init__.py
vmc/models/_base.py
vmc/models/audio.py
vmc/models/embedding.py
vmc/models/gemini/gemini.py
vmc/models/gemini/response_adapter.py
vmc/models/generation.py
vmc/models/openai/openai.py
vmc/models/openai/response_adapter.py
vmc/models/rerank.py
vmc/models/tei/tei.py
vmc/models/tgi/tgi.py
vmc/models/utils.py
vmc/models/vmc/vmc.py
vmc/proxy/__init__.py
vmc/proxy/callback.py
vmc/proxy/manager.py
vmc/proxy/model.py
vmc/proxy/server.py
vmc/proxy/utils.py
vmc/routes/__init__.py
vmc/routes/openai.py
vmc/routes/vmc.py
vmc/routes/wrapper.py
vmc/serve/__init__.py
vmc/serve/callback.py
vmc/serve/manager/client.py
vmc/serve/manager/params.py
vmc/serve/manager/server.py
vmc/serve/models/__init__.py
vmc/serve/models/modules.py
vmc/serve/models/transformers/embedding.py
vmc/serve/models/transformers/generation.py
vmc/serve/models/transformers/rerank.py
vmc/serve/models/whisper/whisper.py
vmc/serve/server.py
vmc/serve/vmm.py
vmc/types/__init__.py
vmc/types/_base.py
vmc/types/_types.py
vmc/types/audio/__init__.py
vmc/types/audio/create.py
vmc/types/audio/transcription.py
vmc/types/auth/__init__.py
vmc/types/auth/auth.py
vmc/types/embedding/__init__.py
vmc/types/embedding/create.py
vmc/types/embedding/embedding.py
vmc/types/errors/__init__.py
vmc/types/errors/_base.py
vmc/types/errors/errors.py
vmc/types/errors/message.py
vmc/types/errors/status_code.py
vmc/types/generation/__init__.py
vmc/types/generation/generation.py
vmc/types/generation/generation_chunk.py
vmc/types/generation/generation_params.py
vmc/types/generation/message.py
vmc/types/generation/message_params.py
vmc/types/generation/named_tool_choice_param.py
vmc/types/generation/tokenize.py
vmc-0.0.10.dist-info/LICENSE
vmc-0.0.10.dist-info/METADATA
vmc-0.0.10.dist-info/WHEEL
vmc-0.0.10.dist-info/entry_points.txt
vmc-0.0.10.dist-info/RECORD
